{
  "generatedAt": "2026-03-01T04:59:13.306Z",
  "implementation": {
    "source": "./apps/api/src/ums/engine.mjs",
    "exportName": "createUmsEngine"
  },
  "config": {
    "events": 2000,
    "queries": 300,
    "maxItems": 10,
    "tokenBudget": 220,
    "stores": [
      "coding-agent",
      "jira-history"
    ]
  },
  "thresholds": {
    "ingestP95Ms": 2.5,
    "replayP95Ms": 2.5,
    "recallP95Ms": 8,
    "recallPayloadMaxBytes": 4096
  },
  "metrics": {
    "ingestMs": {
      "p50": 0.0016,
      "p95": 0.006,
      "max": 0.7358
    },
    "replayMs": {
      "p50": 0.0009,
      "p95": 0.0029,
      "max": 0.4997
    },
    "recallMs": {
      "p50": 2.2008,
      "p95": 3.1205,
      "max": 5.8766
    },
    "recallPayloadBytes": {
      "p50": 3615.5,
      "p95": 3660.75,
      "max": 3675
    },
    "replayDuplicatesCaptured": 4000,
    "byStore": {
      "coding-agent": {
        "ingestMs": {
          "p50": 0.0022,
          "p95": 0.0076,
          "max": 0.7358
        },
        "replayMs": {
          "p50": 0.0009,
          "p95": 0.0033,
          "max": 0.2676
        },
        "recallMs": {
          "p50": 2.2512,
          "p95": 3.208,
          "max": 5.6241
        },
        "recallPayloadBytes": {
          "p50": 3578,
          "p95": 3635,
          "max": 3635
        },
        "replayDuplicatesCaptured": 2000
      },
      "jira-history": {
        "ingestMs": {
          "p50": 0.0015,
          "p95": 0.0018,
          "max": 0.0377
        },
        "replayMs": {
          "p50": 0.001,
          "p95": 0.001,
          "max": 0.4997
        },
        "recallMs": {
          "p50": 2.1037,
          "p95": 2.7072,
          "max": 5.8766
        },
        "recallPayloadBytes": {
          "p50": 3620,
          "p95": 3675,
          "max": 3675
        },
        "replayDuplicatesCaptured": 2000
      }
    }
  },
  "gates": {
    "ingestP95WithinThreshold": true,
    "replayP95WithinThreshold": true,
    "recallP95WithinThreshold": true,
    "recallPayloadMaxWithinThreshold": true,
    "replayCapturedAllDuplicates": true
  },
  "gatesByStore": {
    "coding-agent": {
      "ingestP95WithinThreshold": true,
      "replayP95WithinThreshold": true,
      "recallP95WithinThreshold": true,
      "recallPayloadMaxWithinThreshold": true,
      "replayCapturedAllDuplicates": true
    },
    "jira-history": {
      "ingestP95WithinThreshold": true,
      "replayP95WithinThreshold": true,
      "recallP95WithinThreshold": true,
      "recallPayloadMaxWithinThreshold": true,
      "replayCapturedAllDuplicates": true
    }
  }
}
